<mesh>
  <submeshes>
    <submesh material="attachments" name="weapon_orc_chopa_4" usesharedvertices="false" use32bitindexes="false">
      <faces count="146">
        <face v1="0" v2="1" v3="2" />
        <face v1="3" v2="1" v3="0" />
        <face v1="4" v2="1" v3="3" />
        <face v1="5" v2="4" v3="3" />
        <face v1="6" v2="4" v3="5" />
        <face v1="3" v2="0" v3="7" />
        <face v1="3" v2="7" v3="8" />
        <face v1="8" v2="5" v3="3" />
        <face v1="8" v2="7" v3="9" />
        <face v1="10" v2="9" v3="7" />
        <face v1="9" v2="10" v3="11" />
        <face v1="10" v2="12" v3="11" />
        <face v1="10" v2="13" v3="12" />
        <face v1="13" v2="14" v3="12" />
        <face v1="13" v2="15" v3="14" />
        <face v1="13" v2="16" v3="15" />
        <face v1="17" v2="15" v3="16" />
        <face v1="17" v2="16" v3="18" />
        <face v1="19" v2="15" v3="17" />
        <face v1="5" v2="8" v3="20" />
        <face v1="14" v2="21" v3="12" />
        <face v1="21" v2="14" v3="22" />
        <face v1="22" v2="23" v3="21" />
        <face v1="24" v2="21" v3="23" />
        <face v1="12" v2="24" v3="11" />
        <face v1="12" v2="21" v3="24" />
        <face v1="24" v2="9" v3="11" />
        <face v1="24" v2="23" v3="25" />
        <face v1="26" v2="24" v3="25" />
        <face v1="24" v2="26" v3="27" />
        <face v1="23" v2="22" v3="28" />
        <face v1="28" v2="29" v3="23" />
        <face v1="29" v2="25" v3="23" />
        <face v1="26" v2="30" v3="27" />
        <face v1="30" v2="26" v3="31" />
        <face v1="31" v2="32" v3="30" />
        <face v1="33" v2="32" v3="31" />
        <face v1="34" v2="31" v3="26" />
        <face v1="25" v2="34" v3="26" />
        <face v1="35" v2="31" v3="34" />
        <face v1="31" v2="35" v3="33" />
        <face v1="24" v2="27" v3="9" />
        <face v1="27" v2="8" v3="9" />
        <face v1="8" v2="27" v3="30" />
        <face v1="8" v2="30" v3="32" />
        <face v1="8" v2="32" v3="20" />
        <face v1="25" v2="29" v3="36" />
        <face v1="35" v2="34" v3="36" />
        <face v1="34" v2="25" v3="36" />
        <face v1="37" v2="38" v3="16" />
        <face v1="37" v2="39" v3="38" />
        <face v1="39" v2="37" v3="40" />
        <face v1="40" v2="37" v3="0" />
        <face v1="38" v2="18" v3="16" />
        <face v1="40" v2="0" v3="2" />
        <face v1="37" v2="16" v3="13" />
        <face v1="37" v2="13" v3="10" />
        <face v1="7" v2="37" v3="10" />
        <face v1="37" v2="7" v3="0" />
        <face v1="41" v2="42" v3="43" />
        <face v1="41" v2="44" v3="42" />
        <face v1="44" v2="45" v3="42" />
        <face v1="46" v2="41" v3="43" />
        <face v1="46" v2="43" v3="47" />
        <face v1="4" v2="48" v3="1" />
        <face v1="6" v2="48" v3="4" />
        <face v1="49" v2="50" v3="51" />
        <face v1="51" v2="50" v3="52" />
        <face v1="49" v2="51" v3="53" />
        <face v1="54" v2="53" v3="51" />
        <face v1="55" v2="53" v3="54" />
        <face v1="56" v2="55" v3="54" />
        <face v1="49" v2="57" v3="50" />
        <face v1="50" v2="57" v3="58" />
        <face v1="53" v2="59" v3="49" />
        <face v1="49" v2="59" v3="57" />
        <face v1="53" v2="55" v3="59" />
        <face v1="55" v2="60" v3="59" />
        <face v1="61" v2="51" v3="52" />
        <face v1="62" v2="51" v3="61" />
        <face v1="63" v2="56" v3="54" />
        <face v1="64" v2="63" v3="54" />
        <face v1="55" v2="56" v3="65" />
        <face v1="56" v2="66" v3="65" />
        <face v1="51" v2="67" v3="54" />
        <face v1="67" v2="68" v3="54" />
        <face v1="64" v2="54" v3="69" />
        <face v1="68" v2="69" v3="54" />
        <face v1="70" v2="69" v3="68" />
        <face v1="71" v2="70" v3="68" />
        <face v1="72" v2="70" v3="71" />
        <face v1="73" v2="72" v3="71" />
        <face v1="73" v2="71" v3="74" />
        <face v1="74" v2="71" v3="75" />
        <face v1="67" v2="75" v3="68" />
        <face v1="75" v2="71" v3="68" />
        <face v1="74" v2="75" v3="76" />
        <face v1="76" v2="75" v3="77" />
        <face v1="75" v2="67" v3="77" />
        <face v1="78" v2="72" v3="73" />
        <face v1="79" v2="78" v3="73" />
        <face v1="79" v2="73" v3="80" />
        <face v1="80" v2="73" v3="74" />
        <face v1="80" v2="81" v3="79" />
        <face v1="80" v2="82" v3="81" />
        <face v1="80" v2="74" v3="82" />
        <face v1="82" v2="74" v3="76" />
        <face v1="83" v2="81" v3="82" />
        <face v1="81" v2="83" v3="84" />
        <face v1="81" v2="85" v3="79" />
        <face v1="81" v2="84" v3="85" />
        <face v1="82" v2="76" v3="86" />
        <face v1="86" v2="76" v3="87" />
        <face v1="86" v2="87" v3="88" />
        <face v1="76" v2="89" v3="87" />
        <face v1="90" v2="86" v3="88" />
        <face v1="91" v2="82" v3="86" />
        <face v1="91" v2="86" v3="90" />
        <face v1="82" v2="91" v3="83" />
        <face v1="92" v2="83" v3="91" />
        <face v1="92" v2="84" v3="83" />
        <face v1="93" v2="91" v3="90" />
        <face v1="91" v2="93" v3="92" />
        <face v1="94" v2="92" v3="93" />
        <face v1="94" v2="84" v3="92" />
        <face v1="85" v2="95" v3="79" />
        <face v1="85" v2="84" v3="95" />
        <face v1="78" v2="79" v3="95" />
        <face v1="87" v2="89" v3="96" />
        <face v1="89" v2="97" v3="96" />
        <face v1="96" v2="98" v3="87" />
        <face v1="88" v2="87" v3="98" />
        <face v1="98" v2="96" v3="99" />
        <face v1="100" v2="99" v3="96" />
        <face v1="101" v2="99" v3="100" />
        <face v1="99" v2="101" v3="102" />
        <face v1="103" v2="99" v3="102" />
        <face v1="104" v2="101" v3="100" />
        <face v1="104" v2="100" v3="105" />
        <face v1="100" v2="106" v3="105" />
        <face v1="51" v2="62" v3="97" />
        <face v1="62" v2="107" v3="97" />
        <face v1="67" v2="51" v3="97" />
        <face v1="77" v2="67" v3="97" />
        <face v1="50" v2="108" v3="52" />
        <face v1="52" v2="108" v3="109" />
      </faces>
      <geometry vertexcount="110">
        <vertexbuffer positions="true" normals="true" colours_diffuse="false" texture_coords="1" texture_coords_dimensions_0="2" >
          <vertex>
            <position x="-1.270961" y="-0.326746" z="0.489936" />
            <normal x="-0.113836" y="-0.027478" z="0.993120" />
            <texcoord u="0.862051" v="0.238246" />
          </vertex>
          <vertex>
            <position x="-1.213296" y="-0.222871" z="0.493627" />
            <normal x="0.246314" y="0.191577" z="0.950067" />
            <texcoord u="0.851553" v="0.248990" />
          </vertex>
          <vertex>
            <position x="-1.275193" y="-0.222871" z="0.493626" />
            <normal x="-0.113773" y="-0.043155" z="0.992569" />
            <texcoord u="0.859365" v="0.251430" />
          </vertex>
          <vertex>
            <position x="-1.187142" y="-0.328254" z="0.489936" />
            <normal x="0.451140" y="-0.058844" z="0.890511" />
            <texcoord u="0.851309" v="0.235317" />
          </vertex>
          <vertex>
            <position x="-1.172491" y="-0.265502" z="0.490172" />
            <normal x="0.930314" y="0.247299" z="0.270851" />
            <texcoord u="0.848379" v="0.242641" />
          </vertex>
          <vertex>
            <position x="-1.187142" y="-0.328254" z="0.455271" />
            <normal x="0.995146" y="-0.098335" z="0.003933" />
            <texcoord u="0.847158" v="0.234340" />
          </vertex>
          <vertex>
            <position x="-1.172491" y="-0.265502" z="0.450955" />
            <normal x="0.964574" y="0.263782" z="0.003937" />
            <texcoord u="0.843984" v="0.242641" />
          </vertex>
          <vertex>
            <position x="-1.270961" y="-0.556571" z="0.487822" />
            <normal x="-0.106116" y="0.003930" z="0.994346" />
            <texcoord u="0.867666" v="0.217006" />
          </vertex>
          <vertex>
            <position x="-1.171179" y="-0.781947" z="0.489936" />
            <normal x="0.701950" y="0.058823" z="0.709793" />
            <texcoord u="0.861563" v="0.190395" />
          </vertex>
          <vertex>
            <position x="-1.270961" y="-0.803999" z="0.489936" />
            <normal x="-0.121507" y="-0.043115" z="0.991654" />
            <texcoord u="0.874746" v="0.191371" />
          </vertex>
          <vertex>
            <position x="-1.348607" y="-0.564954" z="0.473210" />
            <normal x="-0.999309" y="0.011757" z="0.035270" />
            <texcoord u="0.877920" v="0.218715" />
          </vertex>
          <vertex>
            <position x="-1.355821" y="-0.817115" z="0.473210" />
            <normal x="-0.958356" y="-0.285551" z="0.003912" />
            <texcoord u="0.886221" v="0.192836" />
          </vertex>
          <vertex>
            <position x="-1.270961" y="-0.803999" z="0.455271" />
            <normal x="-0.145643" y="-0.051172" z="-0.988013" />
            <texcoord u="0.874746" v="0.191371" />
          </vertex>
          <vertex>
            <position x="-1.270961" y="-0.556571" z="0.451418" />
            <normal x="-0.121619" y="0.003923" z="-0.992569" />
            <texcoord u="0.867666" v="0.217006" />
          </vertex>
          <vertex>
            <position x="-1.171179" y="-0.781947" z="0.455271" />
            <normal x="0.027430" y="-0.027430" z="-0.999247" />
            <texcoord u="0.861563" v="0.190395" />
          </vertex>
          <vertex>
            <position x="-1.187142" y="-0.328254" z="0.455271" />
            <normal x="0.003920" y="-0.027440" z="-0.999616" />
            <texcoord u="0.851309" v="0.235317" />
          </vertex>
          <vertex>
            <position x="-1.270961" y="-0.326746" z="0.455271" />
            <normal x="-0.129259" y="-0.035252" z="-0.990984" />
            <texcoord u="0.862051" v="0.238246" />
          </vertex>
          <vertex>
            <position x="-1.213296" y="-0.223245" z="0.449344" />
            <normal x="-0.011744" y="-0.058718" z="-0.998206" />
            <texcoord u="0.851553" v="0.248990" />
          </vertex>
          <vertex>
            <position x="-1.275193" y="-0.223244" z="0.449344" />
            <normal x="-0.145580" y="-0.059019" z="-0.987585" />
            <texcoord u="0.859365" v="0.251430" />
          </vertex>
          <vertex>
            <position x="-1.172491" y="-0.265502" z="0.450955" />
            <normal x="-0.027393" y="-0.058700" z="-0.997900" />
            <texcoord u="0.848379" v="0.242641" />
          </vertex>
          <vertex>
            <position x="-1.171179" y="-0.781947" z="0.455271" />
            <normal x="0.995146" y="0.098335" z="0.003933" />
            <texcoord u="0.858145" v="0.189662" />
          </vertex>
          <vertex>
            <position x="-1.225715" y="-0.907231" z="0.458629" />
            <normal x="-0.051106" y="-0.090417" z="-0.994592" />
            <texcoord u="0.873037" v="0.177211" />
          </vertex>
          <vertex>
            <position x="-1.154000" y="-0.884639" z="0.461582" />
            <normal x="0.050895" y="-0.027405" z="-0.998328" />
            <texcoord u="0.863271" v="0.177211" />
          </vertex>
          <vertex>
            <position x="-1.162499" y="-0.969307" z="0.463002" />
            <normal x="-0.019663" y="-0.098316" z="-0.994961" />
            <texcoord u="0.867422" v="0.167202" />
          </vertex>
          <vertex>
            <position x="-1.277751" y="-0.934200" z="0.473210" />
            <normal x="-0.756200" y="-0.654329" z="0.003918" />
            <texcoord u="0.880605" v="0.175991" />
          </vertex>
          <vertex>
            <position x="-1.181389" y="-1.036532" z="0.473210" />
            <normal x="-0.247146" y="-0.968970" z="-0.003923" />
            <texcoord u="0.872549" v="0.159877" />
          </vertex>
          <vertex>
            <position x="-1.162499" y="-0.969307" z="0.484207" />
            <normal x="-0.003933" y="-0.098335" z="0.995146" />
            <texcoord u="0.867422" v="0.167202" />
          </vertex>
          <vertex>
            <position x="-1.225715" y="-0.907231" z="0.486905" />
            <normal x="-0.058982" y="-0.082575" z="0.994838" />
            <texcoord u="0.873037" v="0.177211" />
          </vertex>
          <vertex>
            <position x="-1.134121" y="-0.937806" z="0.463434" />
            <normal x="0.043081" y="-0.027415" z="-0.998695" />
            <texcoord u="0.862783" v="0.169887" />
          </vertex>
          <vertex>
            <position x="-1.112192" y="-0.976006" z="0.465733" />
            <normal x="0.019663" y="-0.098316" z="-0.994961" />
            <texcoord u="0.861563" v="0.164272" />
          </vertex>
          <vertex>
            <position x="-1.154000" y="-0.884639" z="0.485831" />
            <normal x="0.560500" y="0.121507" z="0.819192" />
            <texcoord u="0.863271" v="0.177211" />
          </vertex>
          <vertex>
            <position x="-1.133379" y="-0.937376" z="0.482467" />
            <normal x="0.835179" y="0.364655" z="0.411708" />
            <texcoord u="0.862783" v="0.169887" />
          </vertex>
          <vertex>
            <position x="-1.154000" y="-0.884639" z="0.461582" />
            <normal x="0.965057" y="0.261777" z="-0.011721" />
            <texcoord u="0.860098" v="0.176967" />
          </vertex>
          <vertex>
            <position x="-1.134121" y="-0.937806" z="0.463434" />
            <normal x="0.906538" y="0.419911" z="-0.043168" />
            <texcoord u="0.860342" v="0.169887" />
          </vertex>
          <vertex>
            <position x="-1.111542" y="-0.975836" z="0.479737" />
            <normal x="0.530678" y="0.208340" z="0.821569" />
            <texcoord u="0.861563" v="0.164272" />
          </vertex>
          <vertex>
            <position x="-1.112192" y="-0.976006" z="0.465733" />
            <normal x="0.860825" y="0.507061" z="-0.043238" />
            <texcoord u="0.859854" v="0.164516" />
          </vertex>
          <vertex>
            <position x="-1.060366" y="-1.059759" z="0.473210" />
            <normal x="0.923146" y="0.381043" z="-0.051068" />
            <texcoord u="0.858633" v="0.152065" />
          </vertex>
          <vertex>
            <position x="-1.343240" y="-0.325036" z="0.473210" />
            <normal x="-0.995700" y="-0.090518" z="0.019678" />
            <texcoord u="0.871328" v="0.240688" />
          </vertex>
          <vertex>
            <position x="-1.308045" y="-0.258618" z="0.461454" />
            <normal x="-0.246827" y="-0.050933" z="-0.967720" />
            <texcoord u="0.864736" v="0.247768" />
          </vertex>
          <vertex>
            <position x="-1.357589" y="-0.264684" z="0.473210" />
            <normal x="-0.972990" y="-0.230548" z="0.011723" />
            <texcoord u="0.871328" v="0.248501" />
          </vertex>
          <vertex>
            <position x="-1.307205" y="-0.257872" z="0.484340" />
            <normal x="-0.222937" y="-0.043023" z="0.973883" />
            <texcoord u="0.864736" v="0.247768" />
          </vertex>
          <vertex>
            <position x="-1.275193" y="-0.223244" z="0.449344" />
            <normal x="-0.528235" y="0.849089" z="-0.003913" />
            <texcoord u="0.880605" v="0.282924" />
          </vertex>
          <vertex>
            <position x="-1.307205" y="-0.257872" z="0.484340" />
            <normal x="-0.560983" y="0.827744" z="-0.011769" />
            <texcoord u="0.874990" v="0.288051" />
          </vertex>
          <vertex>
            <position x="-1.275193" y="-0.222871" z="0.493626" />
            <normal x="-0.263765" y="0.964515" z="-0.011810" />
            <texcoord u="0.875234" v="0.281704" />
          </vertex>
          <vertex>
            <position x="-1.308045" y="-0.258618" z="0.461454" />
            <normal x="-0.458113" y="0.888817" z="-0.011746" />
            <texcoord u="0.877920" v="0.288784" />
          </vertex>
          <vertex>
            <position x="-1.357589" y="-0.264684" z="0.473210" />
            <normal x="-0.129291" y="0.991227" z="-0.027425" />
            <texcoord u="0.874746" v="0.294887" />
          </vertex>
          <vertex>
            <position x="-1.213296" y="-0.223245" z="0.449344" />
            <normal x="-0.003921" y="0.999923" z="-0.011764" />
            <texcoord u="0.882314" v="0.275112" />
          </vertex>
          <vertex>
            <position x="-1.213296" y="-0.222871" z="0.493627" />
            <normal x="-0.003921" y="0.999923" z="-0.011764" />
            <texcoord u="0.877188" v="0.273891" />
          </vertex>
          <vertex>
            <position x="-1.213296" y="-0.223245" z="0.449344" />
            <normal x="0.718787" y="0.695220" z="-0.003928" />
            <texcoord u="0.845938" v="0.250454" />
          </vertex>
          <vertex>
            <position x="-1.306592" y="-0.222610" z="0.447154" />
            <normal x="-0.183769" y="-0.785906" z="-0.590407" />
            <texcoord u="0.900625" v="0.263881" />
          </vertex>
          <vertex>
            <position x="-1.376636" y="-0.190946" z="0.453913" />
            <normal x="-0.631674" y="-0.388421" z="-0.670908" />
            <texcoord u="0.911611" v="0.267543" />
          </vertex>
          <vertex>
            <position x="-1.291755" y="-0.169091" z="0.453892" />
            <normal x="-0.051030" y="0.631985" z="-0.773299" />
            <texcoord u="0.897695" v="0.272182" />
          </vertex>
          <vertex>
            <position x="-1.361409" y="-0.149358" z="0.461597" />
            <normal x="-0.622411" y="0.692872" z="-0.364051" />
            <texcoord u="0.909414" v="0.273891" />
          </vertex>
          <vertex>
            <position x="-1.205944" y="-0.229127" z="0.441215" />
            <normal x="0.003915" y="-0.426736" z="-0.904368" />
            <texcoord u="0.885977" v="0.260463" />
          </vertex>
          <vertex>
            <position x="-1.206747" y="-0.171392" z="0.454901" />
            <normal x="0.152817" y="0.654369" z="-0.740573" />
            <texcoord u="0.885488" v="0.269252" />
          </vertex>
          <vertex>
            <position x="-1.134567" y="-0.229123" z="0.450133" />
            <normal x="0.428553" y="-0.546503" z="-0.719497" />
            <texcoord u="0.875234" v="0.258022" />
          </vertex>
          <vertex>
            <position x="-1.145679" y="-0.153174" z="0.461117" />
            <normal x="0.717107" y="0.568199" z="-0.403618" />
            <texcoord u="0.874502" v="0.269008" />
          </vertex>
          <vertex>
            <position x="-1.306592" y="-0.222610" z="0.495011" />
            <normal x="-0.302068" y="-0.953278" z="0.003923" />
            <texcoord u="0.902822" v="0.257289" />
          </vertex>
          <vertex>
            <position x="-1.376636" y="-0.190946" z="0.488632" />
            <normal x="-0.410850" y="-0.911695" z="0.003913" />
            <texcoord u="0.913564" v="0.262905" />
          </vertex>
          <vertex>
            <position x="-1.205944" y="-0.229127" z="0.505111" />
            <normal x="-0.035272" y="-0.999370" z="0.003919" />
            <texcoord u="0.887686" v="0.251186" />
          </vertex>
          <vertex>
            <position x="-1.134567" y="-0.229123" z="0.498494" />
            <normal x="0.003922" y="-0.999985" z="0.003922" />
            <texcoord u="0.876455" v="0.250942" />
          </vertex>
          <vertex>
            <position x="-1.361409" y="-0.149358" z="0.478393" />
            <normal x="0.271085" y="0.962547" z="0.003929" />
            <texcoord u="0.909658" v="0.276332" />
          </vertex>
          <vertex>
            <position x="-1.291755" y="-0.169091" z="0.486940" />
            <normal x="-0.200293" y="0.970046" z="0.137456" />
            <texcoord u="0.899893" v="0.277065" />
          </vertex>
          <vertex>
            <position x="-1.145679" y="-0.153174" z="0.485780" />
            <normal x="-0.285551" y="0.958356" z="0.003912" />
            <texcoord u="0.873525" v="0.272426" />
          </vertex>
          <vertex>
            <position x="-1.206747" y="-0.171392" z="0.489530" />
            <normal x="0.199117" y="0.979968" z="0.003904" />
            <texcoord u="0.882070" v="0.273647" />
          </vertex>
          <vertex>
            <position x="-1.134567" y="-0.229123" z="0.498494" />
            <normal x="0.989467" y="0.144705" z="0.003911" />
            <texcoord u="0.867910" v="0.258754" />
          </vertex>
          <vertex>
            <position x="-1.145679" y="-0.153174" z="0.485780" />
            <normal x="0.989467" y="0.144705" z="0.003911" />
            <texcoord u="0.871084" v="0.269741" />
          </vertex>
          <vertex>
            <position x="-1.248733" y="-0.158605" z="0.454048" />
            <normal x="-0.238203" y="0.206963" z="-0.948907" />
            <texcoord u="0.895254" v="0.272426" />
          </vertex>
          <vertex>
            <position x="-1.222405" y="-0.158605" z="0.456747" />
            <normal x="0.700916" y="0.223197" z="-0.677422" />
            <texcoord u="0.888174" v="0.271450" />
          </vertex>
          <vertex>
            <position x="-1.222405" y="-0.158605" z="0.488274" />
            <normal x="0.824150" y="0.566359" z="0.003906" />
            <texcoord u="0.884512" v="0.273403" />
          </vertex>
          <vertex>
            <position x="-1.224005" y="0.070475" z="0.491344" />
            <normal x="0.974778" y="-0.223142" z="0.003915" />
            <texcoord u="0.874746" v="0.304409" />
          </vertex>
          <vertex>
            <position x="-1.224005" y="0.070475" z="0.450121" />
            <normal x="0.669426" y="-0.551983" z="-0.497176" />
            <texcoord u="0.881094" v="0.305141" />
          </vertex>
          <vertex>
            <position x="-1.204265" y="0.094241" z="0.501617" />
            <normal x="0.872299" y="-0.488957" z="0.003912" />
            <texcoord u="0.870840" v="0.308315" />
          </vertex>
          <vertex>
            <position x="-1.204265" y="0.094241" z="0.437579" />
            <normal x="0.764929" y="-0.388349" z="-0.513876" />
            <texcoord u="0.878652" v="0.309291" />
          </vertex>
          <vertex>
            <position x="-1.248733" y="0.093361" z="0.420003" />
            <normal x="-0.231711" y="-0.483059" z="-0.844372" />
            <texcoord u="0.886709" v="0.310756" />
          </vertex>
          <vertex>
            <position x="-1.248733" y="0.069950" z="0.444915" />
            <normal x="-0.262709" y="-0.372497" z="-0.890073" />
            <texcoord u="0.886953" v="0.306362" />
          </vertex>
          <vertex>
            <position x="-1.299365" y="0.092972" z="0.473179" />
            <normal x="-0.837396" y="-0.546470" z="0.011794" />
            <texcoord u="0.894277" v="0.312465" />
          </vertex>
          <vertex>
            <position x="-1.279276" y="0.069725" z="0.472811" />
            <normal x="-0.616360" y="-0.184515" z="-0.765542" />
            <texcoord u="0.892324" v="0.307827" />
          </vertex>
          <vertex>
            <position x="-1.198602" y="0.131766" z="0.504840" />
            <normal x="0.997778" y="0.066519" z="0.003913" />
            <texcoord u="0.869131" v="0.314907" />
          </vertex>
          <vertex>
            <position x="-1.198602" y="0.131766" z="0.432676" />
            <normal x="0.775068" y="0.342289" z="-0.531138" />
            <texcoord u="0.877432" v="0.314662" />
          </vertex>
          <vertex>
            <position x="-1.248733" y="0.130776" z="0.412869" />
            <normal x="-0.082382" y="0.090228" z="-0.992508" />
            <texcoord u="0.885732" v="0.315883" />
          </vertex>
          <vertex>
            <position x="-1.248733" y="0.169327" z="0.435480" />
            <normal x="-0.176544" y="0.647328" z="-0.741484" />
            <texcoord u="0.884023" v="0.321743" />
          </vertex>
          <vertex>
            <position x="-1.305771" y="0.130335" z="0.470876" />
            <normal x="-0.984117" y="0.121544" z="-0.129386" />
            <texcoord u="0.893789" v="0.319301" />
          </vertex>
          <vertex>
            <position x="-1.284764" y="0.169063" z="0.471354" />
            <normal x="-0.716315" y="0.677172" z="0.168315" />
            <texcoord u="0.887930" v="0.324916" />
          </vertex>
          <vertex>
            <position x="-1.248733" y="0.189356" z="0.471879" />
            <normal x="0.027439" y="0.999554" z="0.011759" />
            <texcoord u="0.880117" v="0.326137" />
          </vertex>
          <vertex>
            <position x="-1.220607" y="0.169922" z="0.447338" />
            <normal x="0.545829" y="0.757877" z="-0.357341" />
            <texcoord u="0.878164" v="0.320766" />
          </vertex>
          <vertex>
            <position x="-1.248733" y="0.093361" z="0.523620" />
            <normal x="-0.192296" y="-0.459156" z="0.867294" />
            <texcoord u="0.886709" v="0.310756" />
          </vertex>
          <vertex>
            <position x="-1.248733" y="0.069950" z="0.499120" />
            <normal x="-0.232185" y="-0.365986" z="0.901191" />
            <texcoord u="0.886953" v="0.306362" />
          </vertex>
          <vertex>
            <position x="-1.224005" y="0.070475" z="0.491344" />
            <normal x="0.317116" y="-0.465886" z="0.826067" />
            <texcoord u="0.881094" v="0.305141" />
          </vertex>
          <vertex>
            <position x="-1.279276" y="0.069725" z="0.472811" />
            <normal x="-0.607759" y="-0.184288" z="0.772442" />
            <texcoord u="0.892324" v="0.307827" />
          </vertex>
          <vertex>
            <position x="-1.204265" y="0.094241" z="0.501617" />
            <normal x="0.426841" y="-0.309362" z="0.849766" />
            <texcoord u="0.878652" v="0.309291" />
          </vertex>
          <vertex>
            <position x="-1.248733" y="0.130776" z="0.529634" />
            <normal x="-0.160940" y="0.184493" z="0.969567" />
            <texcoord u="0.885732" v="0.315883" />
          </vertex>
          <vertex>
            <position x="-1.248733" y="0.169327" z="0.505383" />
            <normal x="-0.011716" y="0.691264" z="0.722507" />
            <texcoord u="0.884023" v="0.321743" />
          </vertex>
          <vertex>
            <position x="-1.198602" y="0.131766" z="0.504840" />
            <normal x="0.427866" y="0.302254" z="0.851806" />
            <texcoord u="0.877432" v="0.314662" />
          </vertex>
          <vertex>
            <position x="-1.220607" y="0.169922" z="0.490539" />
            <normal x="0.326208" y="0.687789" z="0.648486" />
            <texcoord u="0.878164" v="0.320766" />
          </vertex>
          <vertex>
            <position x="-1.220607" y="0.169922" z="0.490539" />
            <normal x="0.781246" y="0.624211" z="0.003926" />
            <texcoord u="0.873037" v="0.322719" />
          </vertex>
          <vertex>
            <position x="-1.248733" y="-0.158605" z="0.490297" />
            <normal x="-0.230548" y="-0.011723" z="0.972990" />
            <texcoord u="0.895254" v="0.272426" />
          </vertex>
          <vertex>
            <position x="-1.276771" y="-0.158605" z="0.471758" />
            <normal x="-0.632805" y="0.774301" z="0.003930" />
            <texcoord u="0.897207" v="0.275112" />
          </vertex>
          <vertex>
            <position x="-1.222405" y="-0.158605" z="0.488274" />
            <normal x="0.153392" y="0.043265" z="0.987218" />
            <texcoord u="0.888174" v="0.271450" />
          </vertex>
          <vertex>
            <position x="-1.206747" y="-0.171392" z="0.489530" />
            <normal x="0.027367" y="0.144652" z="0.989104" />
            <texcoord u="0.885488" v="0.269252" />
          </vertex>
          <vertex>
            <position x="-1.291755" y="-0.169091" z="0.486940" />
            <normal x="-0.043028" y="0.136908" z="0.989649" />
            <texcoord u="0.897695" v="0.272182" />
          </vertex>
          <vertex>
            <position x="-1.205944" y="-0.229127" z="0.505111" />
            <normal x="-0.003908" y="0.230562" z="0.973050" />
            <texcoord u="0.885977" v="0.260463" />
          </vertex>
          <vertex>
            <position x="-1.134567" y="-0.229123" z="0.498494" />
            <normal x="0.050914" y="0.215405" z="0.975197" />
            <texcoord u="0.875234" v="0.258022" />
          </vertex>
          <vertex>
            <position x="-1.145679" y="-0.153174" z="0.485780" />
            <normal x="0.011780" y="0.168843" z="0.985573" />
            <texcoord u="0.874502" v="0.269008" />
          </vertex>
          <vertex>
            <position x="-1.306592" y="-0.222610" z="0.495011" />
            <normal x="-0.051049" y="0.161000" z="0.985633" />
            <texcoord u="0.900625" v="0.263881" />
          </vertex>
          <vertex>
            <position x="-1.376636" y="-0.190946" z="0.488632" />
            <normal x="-0.035331" y="0.208058" z="0.977478" />
            <texcoord u="0.911611" v="0.267543" />
          </vertex>
          <vertex>
            <position x="-1.361409" y="-0.149358" z="0.478393" />
            <normal x="-0.043028" y="0.254258" z="0.966179" />
            <texcoord u="0.909414" v="0.273891" />
          </vertex>
          <vertex>
            <position x="-1.248733" y="-0.158605" z="0.490297" />
            <normal x="-0.248018" y="0.893652" z="0.373995" />
            <texcoord u="0.897451" v="0.278041" />
          </vertex>
          <vertex>
            <position x="-1.376636" y="-0.190946" z="0.488632" />
            <normal x="-0.939671" y="0.342056" z="0.003932" />
            <texcoord u="0.916006" v="0.270229" />
          </vertex>
          <vertex>
            <position x="-1.361409" y="-0.149358" z="0.478393" />
            <normal x="-0.939671" y="0.342056" z="0.003932" />
            <texcoord u="0.911367" v="0.275356" />
          </vertex>
        </vertexbuffer>
      </geometry>
      <boneassignments>
        <vertexboneassignment vertexindex="0" boneindex="12" weight="1.0" />
        <vertexboneassignment vertexindex="1" boneindex="12" weight="1.0" />
        <vertexboneassignment vertexindex="2" boneindex="12" weight="1.0" />
        <vertexboneassignment vertexindex="3" boneindex="12" weight="1.0" />
        <vertexboneassignment vertexindex="4" boneindex="12" weight="1.0" />
        <vertexboneassignment vertexindex="5" boneindex="12" weight="1.0" />
        <vertexboneassignment vertexindex="6" boneindex="12" weight="1.0" />
        <vertexboneassignment vertexindex="7" boneindex="12" weight="1.0" />
        <vertexboneassignment vertexindex="8" boneindex="12" weight="1.0" />
        <vertexboneassignment vertexindex="9" boneindex="12" weight="1.0" />
        <vertexboneassignment vertexindex="10" boneindex="12" weight="1.0" />
        <vertexboneassignment vertexindex="11" boneindex="12" weight="1.0" />
        <vertexboneassignment vertexindex="12" boneindex="12" weight="1.0" />
        <vertexboneassignment vertexindex="13" boneindex="12" weight="1.0" />
        <vertexboneassignment vertexindex="14" boneindex="12" weight="1.0" />
        <vertexboneassignment vertexindex="15" boneindex="12" weight="1.0" />
        <vertexboneassignment vertexindex="16" boneindex="12" weight="1.0" />
        <vertexboneassignment vertexindex="17" boneindex="12" weight="1.0" />
        <vertexboneassignment vertexindex="18" boneindex="12" weight="1.0" />
        <vertexboneassignment vertexindex="19" boneindex="12" weight="1.0" />
        <vertexboneassignment vertexindex="20" boneindex="12" weight="1.0" />
        <vertexboneassignment vertexindex="21" boneindex="12" weight="1.0" />
        <vertexboneassignment vertexindex="22" boneindex="12" weight="1.0" />
        <vertexboneassignment vertexindex="23" boneindex="12" weight="1.0" />
        <vertexboneassignment vertexindex="24" boneindex="12" weight="1.0" />
        <vertexboneassignment vertexindex="25" boneindex="12" weight="1.0" />
        <vertexboneassignment vertexindex="26" boneindex="12" weight="1.0" />
        <vertexboneassignment vertexindex="27" boneindex="12" weight="1.0" />
        <vertexboneassignment vertexindex="28" boneindex="12" weight="1.0" />
        <vertexboneassignment vertexindex="29" boneindex="12" weight="1.0" />
        <vertexboneassignment vertexindex="30" boneindex="12" weight="1.0" />
        <vertexboneassignment vertexindex="31" boneindex="12" weight="1.0" />
        <vertexboneassignment vertexindex="32" boneindex="12" weight="1.0" />
        <vertexboneassignment vertexindex="33" boneindex="12" weight="1.0" />
        <vertexboneassignment vertexindex="34" boneindex="12" weight="1.0" />
        <vertexboneassignment vertexindex="35" boneindex="12" weight="1.0" />
        <vertexboneassignment vertexindex="36" boneindex="12" weight="1.0" />
        <vertexboneassignment vertexindex="37" boneindex="12" weight="1.0" />
        <vertexboneassignment vertexindex="38" boneindex="12" weight="1.0" />
        <vertexboneassignment vertexindex="39" boneindex="12" weight="1.0" />
        <vertexboneassignment vertexindex="40" boneindex="12" weight="1.0" />
        <vertexboneassignment vertexindex="41" boneindex="12" weight="1.0" />
        <vertexboneassignment vertexindex="42" boneindex="12" weight="1.0" />
        <vertexboneassignment vertexindex="43" boneindex="12" weight="1.0" />
        <vertexboneassignment vertexindex="44" boneindex="12" weight="1.0" />
        <vertexboneassignment vertexindex="45" boneindex="12" weight="1.0" />
        <vertexboneassignment vertexindex="46" boneindex="12" weight="1.0" />
        <vertexboneassignment vertexindex="47" boneindex="12" weight="1.0" />
        <vertexboneassignment vertexindex="48" boneindex="12" weight="1.0" />
        <vertexboneassignment vertexindex="49" boneindex="12" weight="1.0" />
        <vertexboneassignment vertexindex="50" boneindex="12" weight="1.0" />
        <vertexboneassignment vertexindex="51" boneindex="12" weight="1.0" />
        <vertexboneassignment vertexindex="52" boneindex="12" weight="1.0" />
        <vertexboneassignment vertexindex="53" boneindex="12" weight="1.0" />
        <vertexboneassignment vertexindex="54" boneindex="12" weight="1.0" />
        <vertexboneassignment vertexindex="55" boneindex="12" weight="1.0" />
        <vertexboneassignment vertexindex="56" boneindex="12" weight="1.0" />
        <vertexboneassignment vertexindex="57" boneindex="12" weight="1.0" />
        <vertexboneassignment vertexindex="58" boneindex="12" weight="1.0" />
        <vertexboneassignment vertexindex="59" boneindex="12" weight="1.0" />
        <vertexboneassignment vertexindex="60" boneindex="12" weight="1.0" />
        <vertexboneassignment vertexindex="61" boneindex="12" weight="1.0" />
        <vertexboneassignment vertexindex="62" boneindex="12" weight="1.0" />
        <vertexboneassignment vertexindex="63" boneindex="12" weight="1.0" />
        <vertexboneassignment vertexindex="64" boneindex="12" weight="1.0" />
        <vertexboneassignment vertexindex="65" boneindex="12" weight="1.0" />
        <vertexboneassignment vertexindex="66" boneindex="12" weight="1.0" />
        <vertexboneassignment vertexindex="67" boneindex="12" weight="1.0" />
        <vertexboneassignment vertexindex="68" boneindex="12" weight="1.0" />
        <vertexboneassignment vertexindex="69" boneindex="12" weight="1.0" />
        <vertexboneassignment vertexindex="70" boneindex="12" weight="1.0" />
        <vertexboneassignment vertexindex="71" boneindex="12" weight="1.0" />
        <vertexboneassignment vertexindex="72" boneindex="12" weight="1.0" />
        <vertexboneassignment vertexindex="73" boneindex="12" weight="1.0" />
        <vertexboneassignment vertexindex="74" boneindex="12" weight="1.0" />
        <vertexboneassignment vertexindex="75" boneindex="12" weight="1.0" />
        <vertexboneassignment vertexindex="76" boneindex="12" weight="1.0" />
        <vertexboneassignment vertexindex="77" boneindex="12" weight="1.0" />
        <vertexboneassignment vertexindex="78" boneindex="12" weight="1.0" />
        <vertexboneassignment vertexindex="79" boneindex="12" weight="1.0" />
        <vertexboneassignment vertexindex="80" boneindex="12" weight="1.0" />
        <vertexboneassignment vertexindex="81" boneindex="12" weight="1.0" />
        <vertexboneassignment vertexindex="82" boneindex="12" weight="1.0" />
        <vertexboneassignment vertexindex="83" boneindex="12" weight="1.0" />
        <vertexboneassignment vertexindex="84" boneindex="12" weight="1.0" />
        <vertexboneassignment vertexindex="85" boneindex="12" weight="1.0" />
        <vertexboneassignment vertexindex="86" boneindex="12" weight="1.0" />
        <vertexboneassignment vertexindex="87" boneindex="12" weight="1.0" />
        <vertexboneassignment vertexindex="88" boneindex="12" weight="1.0" />
        <vertexboneassignment vertexindex="89" boneindex="12" weight="1.0" />
        <vertexboneassignment vertexindex="90" boneindex="12" weight="1.0" />
        <vertexboneassignment vertexindex="91" boneindex="12" weight="1.0" />
        <vertexboneassignment vertexindex="92" boneindex="12" weight="1.0" />
        <vertexboneassignment vertexindex="93" boneindex="12" weight="1.0" />
        <vertexboneassignment vertexindex="94" boneindex="12" weight="1.0" />
        <vertexboneassignment vertexindex="95" boneindex="12" weight="1.0" />
        <vertexboneassignment vertexindex="96" boneindex="12" weight="1.0" />
        <vertexboneassignment vertexindex="97" boneindex="12" weight="1.0" />
        <vertexboneassignment vertexindex="98" boneindex="12" weight="1.0" />
        <vertexboneassignment vertexindex="99" boneindex="12" weight="1.0" />
        <vertexboneassignment vertexindex="100" boneindex="12" weight="1.0" />
        <vertexboneassignment vertexindex="101" boneindex="12" weight="1.0" />
        <vertexboneassignment vertexindex="102" boneindex="12" weight="1.0" />
        <vertexboneassignment vertexindex="103" boneindex="12" weight="1.0" />
        <vertexboneassignment vertexindex="104" boneindex="12" weight="1.0" />
        <vertexboneassignment vertexindex="105" boneindex="12" weight="1.0" />
        <vertexboneassignment vertexindex="106" boneindex="12" weight="1.0" />
        <vertexboneassignment vertexindex="107" boneindex="12" weight="1.0" />
        <vertexboneassignment vertexindex="108" boneindex="12" weight="1.0" />
        <vertexboneassignment vertexindex="109" boneindex="12" weight="1.0" />
      </boneassignments>
    </submesh>
  </submeshes>
	<skeletonlink name="std_1.0.skeleton"/>
</mesh>
